{"nodes": [{"id": "app_api_router_py", "label": "router.py", "file_type": "code", "source_file": "app\\api\\router.py", "source_location": "L1"}], "edges": [{"source": "app_api_router_py", "target": "fastapi", "relation": "imports_from", "confidence": "EXTRACTED", "source_file": "app\\api\\router.py", "source_location": "L1", "weight": 1.0}, {"source": "app_api_router_py", "target": "app_api_services_access_route", "relation": "imports_from", "confidence": "EXTRACTED", "source_file": "app\\api\\router.py", "source_location": "L3", "weight": 1.0}, {"source": "app_api_router_py", "target": "app_api_services_auth_route", "relation": "imports_from", "confidence": "EXTRACTED", "source_file": "app\\api\\router.py", "source_location": "L4", "weight": 1.0}, {"source": "app_api_router_py", "target": "app_api_services_companies_route", "relation": "imports_from", "confidence": "EXTRACTED", "source_file": "app\\api\\router.py", "source_location": "L5", "weight": 1.0}, {"source": "app_api_router_py", "target": "app_api_services_device_mapping_route", "relation": "imports_from", "confidence": "EXTRACTED", "source_file": "app\\api\\router.py", "source_location": "L6", "weight": 1.0}, {"source": "app_api_router_py", "target": "app_api_services_devices_route", "relation": "imports_from", "confidence": "EXTRACTED", "source_file": "app\\api\\router.py", "source_location": "L7", "weight": 1.0}, {"source": "app_api_router_py", "target": "app_api_services_groups_route", "relation": "imports_from", "confidence": "EXTRACTED", "source_file": "app\\api\\router.py", "source_location": "L8", "weight": 1.0}, {"source": "app_api_router_py", "target": "app_api_services_logs_route", "relation": "imports_from", "confidence": "EXTRACTED", "source_file": "app\\api\\router.py", "source_location": "L9", "weight": 1.0}, {"source": "app_api_router_py", "target": "app_api_services_sites_route", "relation": "imports_from", "confidence": "EXTRACTED", "source_file": "app\\api\\router.py", "source_location": "L10", "weight": 1.0}, {"source": "app_api_router_py", "target": "app_api_services_push_route", "relation": "imports_from", "confidence": "EXTRACTED", "source_file": "app\\api\\router.py", "source_location": "L11", "weight": 1.0}, {"source": "app_api_router_py", "target": "app_api_services_tenants_route", "relation": "imports_from", "confidence": "EXTRACTED", "source_file": "app\\api\\router.py", "source_location": "L12", "weight": 1.0}, {"source": "app_api_router_py", "target": "app_api_services_users_route", "relation": "imports_from", "confidence": "EXTRACTED", "source_file": "app\\api\\router.py", "source_location": "L13", "weight": 1.0}]}